weishaupt_wcm_com/__init__.py
weishaupt_wcm_com/heat_exchanger.py
weishaupt_wcm_com-0.0.10.dist-info/LICENSE
weishaupt_wcm_com-0.0.10.dist-info/METADATA
weishaupt_wcm_com-0.0.10.dist-info/WHEEL
weishaupt_wcm_com-0.0.10.dist-info/top_level.txt
weishaupt_wcm_com-0.0.10.dist-info/RECORD
