Metadata-Version: 2.1
Name: weishaupt-wcm-com
Version: 0.0.10
Summary: Interfacing the Weishaupt WCM-COM module
Home-page: https://github.com/schmiegelt/Py-Weishaupt-WCM-COM
Author: Philip Schmiegelt
Author-email: philip@schmiegelt.it
License: UNKNOWN
Platform: UNKNOWN
Requires-Python: >=3.6
Requires-Dist: requests
